filepursuer/__init__.py
filepursuer/file_scraper.py
filepursuer/filepursuer.py
src/file_scraper.py
src/filepursuer.py
filepursuit-0.1.16.dist-info/LICENSE
filepursuit-0.1.16.dist-info/METADATA
filepursuit-0.1.16.dist-info/WHEEL
filepursuit-0.1.16.dist-info/entry_points.txt
filepursuit-0.1.16.dist-info/top_level.txt
filepursuit-0.1.16.dist-info/RECORD
