Metadata-Version: 2.1
Name: filepursuit
Version: 0.1.16
Summary: A python tool for scraping and downloading files from filepursuit
Home-page: https://gitlab.com/JCatrielLopez/pylocate
Author: JCatrielLopez
Author-email: jcatriel.lopez@gmail.com
License: UNKNOWN
Platform: UNKNOWN
Classifier: Programming Language :: Python :: 3
Classifier: License :: OSI Approved :: MIT License
Classifier: Operating System :: OS Independent
Requires-Python: >=3
Requires-Dist: requests
Requires-Dist: bs4
Requires-Dist: requests-html
Requires-Dist: clint
